<?xml version="1.0" encoding="utf-8" ?><dwsync><file name="jquery.scrollTo.js" server="wiseexposition.com/wiseexposition.com/" local="3428195770" remote="318763443821092430" Dst="-1" /><file name="jquery.ui.autocomplete.js" server="wiseexposition.com/wiseexposition.com/" local="3428195770" remote="318763443821092431" Dst="-1" /><file name="jquery.scrollTo-min.js" server="wiseexposition.com/wiseexposition.com/" local="3428195770" remote="318763443821092430" Dst="-1" /><file name="jquery.ui.autocomplete.match.js" server="wiseexposition.com/wiseexposition.com/" local="3428195770" remote="318763443821092431" Dst="-1" /><file name="iphone.js" server="wiseexposition.com/wiseexposition.com/" local="3428195770" remote="318763443821092430" Dst="-1" /><file name="wp-locale.js" server="wiseexposition.com/wiseexposition.com/" local="3428195771" remote="318763443821092432" Dst="-1" /><file name="caret.js" server="wiseexposition.com/wiseexposition.com/" local="3428195770" remote="318763443821092430" Dst="-1" /><file name="jquery.jeditable.mini.js" server="wiseexposition.com/wiseexposition.com/" local="3428195770" remote="318763443821092430" Dst="-1" /><file name="p2.js" server="wiseexposition.com/wiseexposition.com/" local="3428195771" remote="318763443821092431" Dst="-1" /><file name="spin.js" server="wiseexposition.com/wiseexposition.com/" local="3428195771" remote="318763443821092431" Dst="-1" /><file name="p2.user.bundle.js" server="wiseexposition.com/wiseexposition.com/" local="3428195771" remote="318763443821092431" Dst="-1" /><file name="jquery.jeditable.js" server="wiseexposition.com/wiseexposition.com/" local="3428195770" remote="318763443821092430" Dst="-1" /><file name="jquery.ui.autocomplete.html.js" server="wiseexposition.com/wiseexposition.com/" local="3428195770" remote="318763443821092431" Dst="-1" /><file name="jquery.ui.autocomplete.multiValue.js" server="wiseexposition.com/wiseexposition.com/" local="3428195770" remote="318763443821092431" Dst="-1" /><file name="jquery.ui.autocomplete.css" server="wiseexposition.com/wiseexposition.com/" local="3428195770" remote="318763443821092430" Dst="-1" /></dwsync>